mincss/__init__.py
mincss/__main__.py
mincss/download.js
mincss/main.py
mincss/processor.py
mincss-0.11.6.dist-info/DESCRIPTION.rst
mincss-0.11.6.dist-info/METADATA
mincss-0.11.6.dist-info/RECORD
mincss-0.11.6.dist-info/WHEEL
mincss-0.11.6.dist-info/entry_points.txt
mincss-0.11.6.dist-info/metadata.json
mincss-0.11.6.dist-info/top_level.txt
tests/__init__.py
tests/test_mincss.py
