Metadata-Version: 2.0
Name: mincss
Version: 0.11.6
Summary: clears the junk out of your CSS
Home-page: https://github.com/peterbe/mincss
Author: Peter Bengtsson
Author-email: mail@peterbe.com
License: BSD
Platform: UNKNOWN
Classifier: Development Status :: 4 - Beta
Classifier: Intended Audience :: Developers
Classifier: License :: OSI Approved :: BSD License
Classifier: Operating System :: OS Independent
Classifier: Programming Language :: Python
Classifier: Programming Language :: Python :: 2
Classifier: Programming Language :: Python :: 2.7
Classifier: Programming Language :: Python :: 3.3
Classifier: Programming Language :: Python :: 3.4
Classifier: Programming Language :: Python :: 3.5
Requires-Dist: lxml
Requires-Dist: cssselect
